nanoindentation/__init__.py
nanoindentation/calibration.py
nanoindentation/definitions.py
nanoindentation/hertz.py
nanoindentation/input.py
nanoindentation/main.py
nanoindentation/names.json
nanoindentation/plot.py
nanoindentation/seldomUsedFunctions.py
nanoindentation/theory.py
nanoindentation/tip.py
nanoindentation/tutorialAdvanced.py
nanoindentation/tutorialBasic.py
nanoindentation/tutorialInstallation.py
nanoindentation/verification.py
nanoindentation/data/Example.xls
nanoindentation-1.0.0.dist-info/METADATA
nanoindentation-1.0.0.dist-info/WHEEL
nanoindentation-1.0.0.dist-info/licenses/LICENSE
nanoindentation-1.0.0.dist-info/RECORD
