Metadata-Version: 2.1
Name: nanoindentation
Version: 1.0.0
Summary: Investigation of nanoindentation data
Project-URL: Homepage, https://micromechanics.readthedocs.io/en/main/
Project-URL: Bug Tracker, https://github.com/micromechanics/main/issues
Author-email: Steffen Brinckmann <sbrinckm@gmail.com>
License-File: LICENSE
Classifier: License :: OSI Approved :: MIT License
Classifier: Operating System :: OS Independent
Classifier: Programming Language :: Python :: 3
Requires-Python: >=3.7
Requires-Dist: h5py>=3.7.0
Requires-Dist: lmfit>=1.0.1
Requires-Dist: matplotlib>=1.1.1
Requires-Dist: numpy>=1.19.2
Requires-Dist: pandas>=1.1.3
Requires-Dist: scipy>=1.5.3
Requires-Dist: xlrd>=1.2.0
